src1/__init__.py
src1/aytlib1.py
src1/src1_1/__init__.py
src1/src1_1/aytlib1_1.py
src2/__init__.py
src2/aytlib2.py
aytlib-0.0.5.dist-info/LICENSE
aytlib-0.0.5.dist-info/METADATA
aytlib-0.0.5.dist-info/WHEEL
aytlib-0.0.5.dist-info/top_level.txt
aytlib-0.0.5.dist-info/RECORD
